tflite_micro/__init__.py
tflite_micro/python/tflite_micro/_runtime.so
tflite_micro/python/tflite_micro/_version.py
tflite_micro/python/tflite_micro/postinstall_check.py
tflite_micro/python/tflite_micro/runtime.py
tflite_micro/python/tflite_micro/sine_float.tflite
tflite_micro/tensorflow/lite/micro/compression/__init__.py
tflite_micro/tensorflow/lite/micro/compression/compress.py
tflite_micro/tensorflow/lite/micro/compression/metadata_py_generated.py
tflite_micro/tensorflow/lite/micro/compression/model_facade.py
tflite_micro/tensorflow/lite/micro/compression/spec.py
tflite_micro/tensorflow/lite/micro/compression/spec_builder.py
tflite_micro/tensorflow/lite/micro/tools/generate_test_for_model.py
tflite_micro/tensorflow/lite/micro/tools/tflite_flatbuffer_align
tflite_micro/tensorflow/lite/micro/tools/tflite_flatbuffer_align.py
tflite_micro/tensorflow/lite/micro/tools/tflite_flatbuffer_align_wrapper.so
tflite_micro/tensorflow/lite/python/schema_py_generated.py
tflite_micro/tensorflow/lite/python/schema_util.py
tflite_micro/tensorflow/lite/tools/flatbuffer_utils.py
tflite_micro-0.dev20260131234035.dist-info/METADATA
tflite_micro-0.dev20260131234035.dist-info/RECORD
tflite_micro-0.dev20260131234035.dist-info/WHEEL
