Metadata-Version: 2.1
Name: tflite_micro
Summary: TensorFlow Lite for Microcontrollers
Requires-Dist: bitarray
Requires-Dist: flatbuffers
Requires-Dist: numpy
Requires-Dist: pyyaml
Requires-Dist: tensorflow
Version: 0.dev20260131234035
